tarzi-0.1.9.dist-info/RECORD
tarzi-0.1.9.dist-info/WHEEL
tarzi-0.1.9.dist-info/entry_points.txt
tarzi-0.1.9.dist-info/METADATA
tarzi-0.1.9.dist-info/licenses/LICENSE
tarzi/__init__.py
tarzi/tarzi.cpython-313-darwin.so
tarzi/__main__.py
