Metadata-Version: 2.4
Name: tarzi
Version: 0.1.9
Classifier: Development Status :: 4 - Beta
Classifier: Intended Audience :: Developers
Classifier: License :: OSI Approved :: Apache Software License
Classifier: Operating System :: OS Independent
Classifier: Programming Language :: Rust
Classifier: Programming Language :: Python :: 3
Classifier: Programming Language :: Python :: 3.10
Classifier: Programming Language :: Python :: 3.11
Classifier: Programming Language :: Python :: 3.12
Classifier: Programming Language :: Python :: 3.13
Classifier: Programming Language :: Python :: 3.14
Classifier: Topic :: Internet :: WWW/HTTP :: Indexing/Search
Classifier: Topic :: Scientific/Engineering :: Artificial Intelligence
Classifier: Topic :: Software Development :: Libraries :: Python Modules
Requires-Dist: maturin>=1.5,<2.0 ; extra == 'dev'
Requires-Dist: pytest>=7.4,<9 ; extra == 'dev'
Requires-Dist: pytest-asyncio>=0.21,<0.25 ; extra == 'dev'
Requires-Dist: pytest-cov>=0.6 ; extra == 'dev'
Requires-Dist: pytest-mock>=0.1.0 ; extra == 'dev'
Requires-Dist: docopt>=0.6.2 ; extra == 'dev'
Requires-Dist: patchelf>=0.17.2.0 ; sys_platform == 'linux' and extra == 'dev'
Requires-Dist: black>=23.12,<25 ; extra == 'dev'
Requires-Dist: ruff>=0.3,<0.6 ; extra == 'dev'
Requires-Dist: isort>=5.13,<6 ; extra == 'dev'
Requires-Dist: autoflake>=2.2,<3 ; extra == 'dev'
Requires-Dist: twine>=4.0,<6 ; extra == 'dev'
Requires-Dist: build>=1.0,<2 ; extra == 'dev'
Requires-Dist: sphinx>=6.0.0 ; extra == 'docs'
Requires-Dist: sphinx-copybutton>=0.5.2 ; extra == 'docs'
Requires-Dist: myst-parser>=2.0.0 ; extra == 'docs'
Requires-Dist: sphinx-tabs>=3.4.1 ; extra == 'docs'
Requires-Dist: sphinx-design>=0.5.0 ; extra == 'docs'
Requires-Dist: furo>=2023.9.10 ; extra == 'docs'
Requires-Dist: sphinx-autoapi>=3.0.0 ; extra == 'docs'
Provides-Extra: dev
Provides-Extra: docs
License-File: LICENSE
Summary: Rust-native lite search for AI applications
Keywords: web-scraping,search-engine,ai-tools,rust,browser-automation
Author-email: Xiaming Chen <chenxm35@gmail.com>
Maintainer-email: Xiaming Chen <chenxm35@gmail.com>
License: Apache-2.0
Requires-Python: >=3.10
Project-URL: Homepage, https://github.com/mirasoth/tarzi
Project-URL: Documentation, https://tarzi.readthedocs.io/
Project-URL: Repository, https://github.com/mirasoth/tarzi
